README.md
setup.py
src/aeroterra_ds.egg-info/PKG-INFO
src/aeroterra_ds.egg-info/SOURCES.txt
src/aeroterra_ds.egg-info/dependency_links.txt
src/aeroterra_ds.egg-info/requires.txt
src/aeroterra_ds.egg-info/top_level.txt
src/exceptions/__init__.py
src/exceptions/type_checker.py
src/geometry/__init__.py
src/geometry/change_crs.py
src/geometry/checks.py
src/geometry/common.py
src/geometry/dataframes.py
src/geometry/distance.py
src/geometry/filters.py
src/geometry/geometry.py
src/geometry/polygons.py
src/gis_typing/__init__.py
src/gis_typing/gis_types.py
src/layers/__init__.py
src/layers/checks.py
src/layers/common.py
src/layers/constants.py
src/layers/fields.py
src/layers/gets.py
src/layers/imagery.py
src/layers/layers.py
src/layers/mapping.py
src/layers/properties.py
src/layers/symbology.py
src/rasters/__init__.py
src/rasters/common.py
src/rasters/handler.py
src/rasters/polygons.py
src/rasters/properties.py