Metadata-Version: 2.1
Name: aeroterra-ds
Version: 2.0.2.0
Summary: Python Functions To Work With GeoSpatial Data & ArcGis in a simpler way
Home-page: https://example.com
Author: Data Science
Author-email: aeroterra_ds@aeroterra.com
Keywords: arcgis
Classifier: Programming Language :: Python :: 3
Classifier: License :: OSI Approved :: MIT License
Classifier: Operating System :: OS Independent
Requires-Python: >=3.9
